<?xml version="1.0" encoding="UTF-8"?>
<annotation>
  <filename>2791.jpg</filename>
  <object_num>2</object_num>
  <size>
    <width>320</width>
    <height>240</height>
  </size>
  <object>
    <name>granary</name>
    <difficult>0</difficult>
    <bndbox>
      <xmin>33</xmin>
      <ymin>21</ymin>
      <xmax>59</xmax>
      <ymax>46</ymax>
    </bndbox>
  </object>
  <object>
    <name>granary</name>
    <difficult>0</difficult>
    <bndbox>
      <xmin>264</xmin>
      <ymin>19</ymin>
      <xmax>293</xmax>
      <ymax>46</ymax>
    </bndbox>
  </object>
</annotation>