<?xml version="1.0" encoding="UTF-8"?>
<annotation>
  <filename>3087.jpg</filename>
  <object_num>2</object_num>
  <size>
    <width>320</width>
    <height>240</height>
  </size>
  <object>
    <name>granary</name>
    <difficult>0</difficult>
    <bndbox>
      <xmin>19</xmin>
      <ymin>24</ymin>
      <xmax>45</xmax>
      <ymax>50</ymax>
    </bndbox>
  </object>
  <object>
    <name>granary</name>
    <difficult>0</difficult>
    <bndbox>
      <xmin>40</xmin>
      <ymin>14</ymin>
      <xmax>60</xmax>
      <ymax>31</ymax>
    </bndbox>
  </object>
</annotation>