<?xml version="1.0" encoding="UTF-8"?>
<annotation>
  <filename>3543.jpg</filename>
  <object_num>2</object_num>
  <size>
    <width>320</width>
    <height>240</height>
  </size>
  <object>
    <name>tractor</name>
    <difficult>0</difficult>
    <bndbox>
      <xmin>146</xmin>
      <ymin>11</ymin>
      <xmax>210</xmax>
      <ymax>61</ymax>
    </bndbox>
  </object>
  <object>
    <name>tractor</name>
    <difficult>0</difficult>
    <bndbox>
      <xmin>65</xmin>
      <ymin>46</ymin>
      <xmax>153</xmax>
      <ymax>124</ymax>
    </bndbox>
  </object>
</annotation>