<?xml version="1.0" encoding="UTF-8"?>
<annotation>
  <filename>3810.jpg</filename>
  <object_num>2</object_num>
  <size>
    <width>320</width>
    <height>240</height>
  </size>
  <object>
    <name>bridge</name>
    <difficult>0</difficult>
    <bndbox>
      <xmin>0</xmin>
      <ymin>78</ymin>
      <xmax>45</xmax>
      <ymax>117</ymax>
    </bndbox>
  </object>
  <object>
    <name>bridge</name>
    <difficult>0</difficult>
    <bndbox>
      <xmin>253</xmin>
      <ymin>61</ymin>
      <xmax>311</xmax>
      <ymax>99</ymax>
    </bndbox>
  </object>
</annotation>